[
  {
    "mapId": "Beryö§ƤØŢĀŤ0Co,",
    "map": "Beryö",
    "author": "ƤØŢĀŤ0Co,",
    "player": "mate108",
    "time": "10.46",
    "timeCentiseconds": 1046,
    "file": "Beryö§ƤØŢĀŤ0Co,_mate108_10.46.demo",
    "demo": "Beryö§ƤØŢĀŤ0Co,_mate108_10.46.demo",
    "mapDownload": "maps/Bery%C3%B6%C2%A7%C6%A4%C3%98%C5%A2%C4%80%C5%A40Co%2C.map",
    "mapFile": "Beryö§ƤØŢĀŤ0Co,.map",
    "video": "https://kinescope.io/nR7yv1t5Y1S4oUS6K7sTQy",
    "videoEmbed": "https://kinescope.io/embed/nR7yv1t5Y1S4oUS6K7sTQy",
    "videoSource": "kinescope"
  },
  {
    "mapId": "Cheesy§DoubleDipp,",
    "map": "Cheesy",
    "author": "DoubleDipp,",
    "player": "67",
    "time": "15.00",
    "timeCentiseconds": 1500,
    "file": "Cheesy§DoubleDipp,_67_15.00.demo",
    "demo": "Cheesy§DoubleDipp,_67_15.00.demo",
    "mapDownload": "maps/Cheesy%C2%A7DoubleDipp%2C.map",
    "mapFile": "Cheesy§DoubleDipp,.map",
    "video": "https://kinescope.io/xpuGhBA5wq99f58vbKTHco",
    "videoEmbed": "https://kinescope.io/embed/xpuGhBA5wq99f58vbKTHco",
    "videoSource": "kinescope"
  },
  {
    "mapId": "Dustfall_1111§texnonik,",
    "map": "Dustfall_1111",
    "author": "texnonik,",
    "player": "girlkitten _3c",
    "time": "11.14",
    "timeCentiseconds": 1114,
    "file": "Dustfall_1111§texnonik,_girlkitten _3c_11.14.demo",
    "demo": "Dustfall_1111§texnonik,_girlkitten _3c_11.14.demo",
    "mapDownload": "maps/Dustfall_1111%C2%A7texnonik%2C.map",
    "mapFile": "Dustfall_1111§texnonik,.map",
    "video": "https://kinescope.io/eSMsxaQv2FBiD2rbUTiHAs",
    "videoEmbed": "https://kinescope.io/embed/eSMsxaQv2FBiD2rbUTiHAs",
    "videoSource": "kinescope"
  },
  {
    "mapId": "Föret§ƤØŢĀŤ0Co,",
    "map": "Föret",
    "author": "ƤØŢĀŤ0Co,",
    "player": "Namzar",
    "time": "8.50",
    "timeCentiseconds": 850,
    "file": "Föret§ƤØŢĀŤ0Co,_Namzar_08.50.demo",
    "demo": "Föret§ƤØŢĀŤ0Co,_Namzar_08.50.demo",
    "mapDownload": "maps/F%C3%B6ret%C2%A7%C6%A4%C3%98%C5%A2%C4%80%C5%A40Co%2C.map",
    "mapFile": "Föret§ƤØŢĀŤ0Co,.map",
    "video": "https://kinescope.io/6y9GzQs7wswDMsCmsHpmyP",
    "videoEmbed": "https://kinescope.io/embed/6y9GzQs7wswDMsCmsHpmyP",
    "videoSource": "kinescope"
  },
  {
    "mapId": "Heärl§ƤØŢĀŤ0Co,",
    "map": "Heärl",
    "author": "ƤØŢĀŤ0Co,",
    "player": "Vappy",
    "time": "10.88",
    "timeCentiseconds": 1088,
    "file": "Heärl§ƤØŢĀŤ0Co,_Vappy_10.88.demo",
    "demo": "Heärl§ƤØŢĀŤ0Co,_Vappy_10.88.demo",
    "mapDownload": "maps/He%C3%A4rl%C2%A7%C6%A4%C3%98%C5%A2%C4%80%C5%A40Co%2C.map",
    "mapFile": "Heärl§ƤØŢĀŤ0Co,.map",
    "video": "https://kinescope.io/44WCmNbv4jsxAhgSyRX17X",
    "videoEmbed": "https://kinescope.io/embed/44WCmNbv4jsxAhgSyRX17X",
    "videoSource": "kinescope"
  },
  {
    "mapId": "KurdeBober§Chougune,",
    "map": "KurdeBober",
    "author": "Chougune,",
    "player": "Namzar",
    "time": "11.86",
    "timeCentiseconds": 1186,
    "file": "KurdeBober§Chougune,_Namzar_11.86.demo",
    "demo": "KurdeBober§Chougune,_Namzar_11.86.demo",
    "mapDownload": "maps/KurdeBober%C2%A7Chougune%2C.map",
    "mapFile": "KurdeBober§Chougune,.map",
    "video": "https://kinescope.io/qn7JQ1DnvVzgkob67LMdyB",
    "videoEmbed": "https://kinescope.io/embed/qn7JQ1DnvVzgkob67LMdyB",
    "videoSource": "kinescope"
  },
  {
    "mapId": "per§texnonik,",
    "map": "per",
    "author": "texnonik,",
    "player": "girlkitten _3c",
    "time": "11.58",
    "timeCentiseconds": 1158,
    "file": "per§texnonik,_girlkitten _3c_11.58.demo",
    "demo": "per§texnonik,_girlkitten _3c_11.58.demo",
    "mapDownload": "maps/per%C2%A7texnonik%2C.map",
    "mapFile": "per§texnonik,.map",
    "video": "https://kinescope.io/ariUBwYFvHCP1MMkphweBM",
    "videoEmbed": "https://kinescope.io/embed/ariUBwYFvHCP1MMkphweBM",
    "videoSource": "kinescope"
  },
  {
    "mapId": "percent4§texnonik,",
    "map": "percent4",
    "author": "texnonik,",
    "player": "girlkitten _3c",
    "time": "9.88",
    "timeCentiseconds": 988,
    "file": "percent4§texnonik,_girlkitten _3c_09.88.demo",
    "demo": "percent4§texnonik,_girlkitten _3c_09.88.demo",
    "mapDownload": "maps/percent4%C2%A7texnonik%2C.map",
    "mapFile": "percent4§texnonik,.map",
    "video": "https://kinescope.io/ci5ykozbiqpBt9o2r9Syk8",
    "videoEmbed": "https://kinescope.io/embed/ci5ykozbiqpBt9o2r9Syk8",
    "videoSource": "kinescope"
  },
  {
    "mapId": "Swёrv§ƤØŢĀŤ0Co,",
    "map": "Swёrv",
    "author": "ƤØŢĀŤ0Co,",
    "player": "chujozo100x",
    "time": "11.12",
    "timeCentiseconds": 1112,
    "file": "Swёrv§ƤØŢĀŤ0Co,_chujozo100x_11.12.demo",
    "demo": "Swёrv§ƤØŢĀŤ0Co,_chujozo100x_11.12.demo",
    "mapDownload": "maps/Sw%D1%91rv%C2%A7%C6%A4%C3%98%C5%A2%C4%80%C5%A40Co%2C.map",
    "mapFile": "Swёrv§ƤØŢĀŤ0Co,.map",
    "video": "https://kinescope.io/srvm5MS3sDNAjD1FEtPL2R",
    "videoEmbed": "https://kinescope.io/embed/srvm5MS3sDNAjD1FEtPL2R",
    "videoSource": "kinescope"
  },
  {
    "mapId": "Ёrity§ƤØŢĀŤ0Co,",
    "map": "Ёrity",
    "author": "ƤØŢĀŤ0Co,",
    "player": "камушек",
    "time": "15.82",
    "timeCentiseconds": 1582,
    "file": "Ёrity§ƤØŢĀŤ0Co,_камушек_15.82.demo",
    "demo": "Ёrity§ƤØŢĀŤ0Co,_камушек_15.82.demo",
    "mapDownload": "maps/%D0%81rity%C2%A7%C6%A4%C3%98%C5%A2%C4%80%C5%A40Co%2C.map",
    "mapFile": "Ёrity§ƤØŢĀŤ0Co,.map",
    "video": "https://kinescope.io/jxctcYkKtsWyxy3iwvikqZ",
    "videoEmbed": "https://kinescope.io/embed/jxctcYkKtsWyxy3iwvikqZ",
    "videoSource": "kinescope"
  }
]
